kraken_schema_org/__init__.py
kraken_schema_org/class_kraken_schema_class.py
kraken_schema_org/class_kraken_schema_property.py
kraken_schema_org/class_kraken_schema_record.py
kraken_schema_org/flask_routes.py
kraken_schema_org/kraken_schema_org.py
kraken_schema_org/data/classes.json
kraken_schema_org/data/properties.json
kraken_schema_org/data/properties_definition.json
kraken_schema_org/data/schemas.json
kraken_schema_org/helpers/__init__.py
kraken_schema_org/helpers/json.py
kraken_schema_org/helpers/kraken_db/__init__.py
kraken_schema_org/helpers/kraken_db/kraken_db.py
kraken_schema_org/helpers/kraken_record_id/__init__.py
kraken_schema_org/helpers/kraken_record_id/kraken_record_id.py
kraken_schema_org/helpers/schema_org_id/__init__.py
kraken_schema_org/helpers/schema_org_id/schema_org_id.py
kraken_schema_org/helpers/schema_org_key_mapping/__init__.py
kraken_schema_org/helpers/schema_org_key_mapping/schema_org_key_mapping.py
kraken_schema_org/helpers/schema_org_localize/__init__.py
kraken_schema_org/helpers/schema_org_localize/schema_org_localize.py
kraken_schema_org/helpers/schema_org_name/__init__.py
kraken_schema_org/helpers/schema_org_name/schema_org_name.py
kraken_schema_org/helpers/schema_org_normalizer/__init__.py
kraken_schema_org/helpers/schema_org_normalizer/schema_org_normalizer.py
kraken_schema_org/helpers/schema_org_sample_data/__init__.py
kraken_schema_org/helpers/schema_org_sample_data/schema_org_sample_data.py
kraken_schema_org/helpers/schema_org_summary/__init__.py
kraken_schema_org/helpers/schema_org_summary/schema_org_summary.py
kraken_schema_org/helpers/schema_org_to_json_schema/__init__.py
kraken_schema_org/helpers/schema_org_to_json_schema/schema_org_to_json_schema.py
kraken_schema_org/helpers/schema_org_types/__init__.py
kraken_schema_org/helpers/schema_org_types/schema_org_types.py
kraken_schema_org/helpers/schema_org_website_data/__init__.py
kraken_schema_org/helpers/schema_org_website_data/schema_org_website_data.py
kraken_schema_org-0.1.9.dist-info/LICENSE.txt
kraken_schema_org-0.1.9.dist-info/METADATA
kraken_schema_org-0.1.9.dist-info/WHEEL
kraken_schema_org-0.1.9.dist-info/top_level.txt
kraken_schema_org-0.1.9.dist-info/RECORD
