Metadata-Version: 2.1
Name: kraken-schema-org
Version: 0.1.9
Summary: kraken-schema-org
Home-page: https://github.com/tactik8/krakenschemaorg
Author: Tactik8
Author-email: info@tactik8.com
License: MIT
Classifier: License :: OSI Approved :: MIT License
Classifier: Programming Language :: Python :: 3
Classifier: Programming Language :: Python :: 3.10
License-File: LICENSE.txt
Requires-Dist: kraken-datatype
Requires-Dist: requests
Requires-Dist: Unidecode
Requires-Dist: setuptools
